meu_pacote_imagem/__init__.py
meu_pacote_imagem/processamento.py
meu_pacote_imagem-0.1.0.dist-info/LICENSE
meu_pacote_imagem-0.1.0.dist-info/METADATA
meu_pacote_imagem-0.1.0.dist-info/WHEEL
meu_pacote_imagem-0.1.0.dist-info/top_level.txt
meu_pacote_imagem-0.1.0.dist-info/RECORD
